is_wordpress/__init__.py
is_wordpress/cli.py
is_wordpress/get_requests.py
is_wordpress/parser.py
is_wordpress/run.py
is_wordpress-0.0.2.dist-info/LICENSE
is_wordpress-0.0.2.dist-info/METADATA
is_wordpress-0.0.2.dist-info/WHEEL
is_wordpress-0.0.2.dist-info/entry_points.txt
is_wordpress-0.0.2.dist-info/top_level.txt
is_wordpress-0.0.2.dist-info/RECORD
