Metadata-Version: 2.1
Name: is-wordpress
Version: 0.0.2
Summary: A simple (or useless) Program to check if a website is based on wordpress or not and if it's on wordpress which version does it use.
Home-page: https://github.com/numb95/is_wordpress
Author: AmirHossein Goodarzi
Author-email: amir@goodarzi.net
License: UNKNOWN
Download-URL: https://github.com/numb95/is_wordpress/archive/0.0.2.tar.gz
Platform: UNKNOWN
Classifier: Programming Language :: Python :: 3
Classifier: License :: OSI Approved :: MIT License
Classifier: Operating System :: OS Independent
Requires-Dist: beautifulsoup4 (==4.7.1)
Requires-Dist: bs4 (==0.0.1)
Requires-Dist: certifi (==2018.11.29)
Requires-Dist: chardet (==3.0.4)
Requires-Dist: idna (==2.8)
Requires-Dist: requests (==2.21.0)
Requires-Dist: soupsieve (==1.7.3)
Requires-Dist: urllib3 (==1.24.1)
